{
  "name": "technohud",
  "author": "techno",
  "verified": true,
  "releaseDate": "2024-01-11",
  "social": {
    "steam_profile": "76561198172101254",
    "discord": "rc4322#0",
    "album": "https://imgur.com/a/aHdoUKi"
  },
  "flags": [
    "fonts",
    "menus",
    "materials",
    "customization"
  ],
  "traits": {
    "os": [
      "windows",
      "linux"
    ],
    "gamemode": [
      "tournament",
      "comp",
      "ad",
      "cp",
      "koth",
      "mannpower",
      "pl",
      "plr",
      "ctf",
      "sd",
      "mvm",
      "pass",
      "rd",
      "halloween"
    ],
    "res": [
      "4/3",
      "16/9",
      "16/10"
    ],
    "position": [
      "center"
    ],
    "lang": [
      "en"
    ]
  },
  "tags": [
    "light",
    "minimal",
    "monochrome"
  ],
  "repo": "https://github.com/tekunotri/technohud",
  "hash": "c0a726a841ace48c3a4f3089895779e55ac693b4",
  "prerelease": false,
  "resources": [
    "th-banner",
    "th-menu",
    "th-customizations",
    "th-backpack",
    "th-loadout",
    "th-gameplay",
    "th-scoreboard",
    "th-demoman",
    "th-engineer",
    "th-medic",
    "th-spy",
    "th-ctf",
    "th-mvm",
    "th-altfont"
  ]
}
